services/ApiFlightRadar.py
services/BaseService.py
services/ServiceAirline.py
services/ServiceAirport.py
services/ServiceCountries.py
services/ServiceFactory.py
services/ServiceFlight.py
services/ServiceRegionalFlight.py
services/SparkManager.py
services/__init__.py
badr_g_flight_radar-1.0.dist-info/METADATA
badr_g_flight_radar-1.0.dist-info/WHEEL
badr_g_flight_radar-1.0.dist-info/top_level.txt
badr_g_flight_radar-1.0.dist-info/RECORD
