Metadata-Version: 2.1
Name: badr-g-flight-radar
Version: 1.0
Summary: An ETL tool for Flight Radar data processing
Home-page: https://gitlab.com/Badr_gadi/
Author: Badr Badr
Author-email: badr.gadi.123@gmail.com
Requires-Python: >=3.6
Requires-Dist: pyspark
Requires-Dist: FlightRadar24
Requires-Dist: pandas
Requires-Dist: apscheduler
